pygtt/__init__.py
pygtt-1.1.2.dist-info/METADATA
pygtt-1.1.2.dist-info/RECORD
pygtt-1.1.2.dist-info/WHEEL
pygtt-1.1.2.dist-info/top_level.txt
