Metadata-Version: 2.1
Name: pygtt
Version: 1.1.2
Summary: A python package to get GTT transit info
Home-page: https://github.com/eliseomartelli/pygtt
Author: Eliseo Martelli
Author-email: me@eliseomartelli.it
License: UNKNOWN
Platform: UNKNOWN
Classifier: Programming Language :: Python :: 3
Classifier: License :: OSI Approved :: MIT License
Classifier: Operating System :: OS Independent
Requires-Dist: requests (>=2.0)
Requires-Dist: beautifulsoup4
